{
    "1992-01-01": {
        "Tax Revenues": {
            "order": [
                0,
                0,
                5
            ],
            "seasonal_order": [
                0,
                0,
                1,
                12
            ],
            "gru_mape": 29.998743057250977,
            "gru_rmse": 96004.09375,
            "hybrid_mape": 28.1948745626903,
            "hybrid_rmse": 93821.18739682507
        },
        "BIR": {
            "order": [
                0,
                0,
                2
            ],
            "seasonal_order": [
                0,
                0,
                1,
                3
            ],
            "gru_mape": 28.406814575195312,
            "gru_rmse": 70332.0703125,
            "hybrid_mape": 28.064767384589928,
            "hybrid_rmse": 69961.3895869827
        },
        "BOC": {
            "order": [
                0,
                0,
                2
            ],
            "seasonal_order": [
                1,
                0,
                0,
                3
            ],
            "gru_mape": 40.96364212036133,
            "gru_rmse": 29609.830078125,
            "hybrid_mape": 37.97816962639285,
            "hybrid_rmse": 28892.25652319008
        },
        "Other Offices": {
            "order": [
                0,
                0,
                0
            ],
            "seasonal_order": [
                0,
                0,
                1,
                3
            ],
            "gru_mape": 25.139904022216797,
            "gru_rmse": 685.4837036132812,
            "hybrid_mape": 24.98663205144908,
            "hybrid_rmse": 684.9128684616404
        },
        "Expenditures": {
            "order": [
                5,
                0,
                2
            ],
            "seasonal_order": [
                0,
                1,
                1,
                6
            ],
            "gru_mape": 44.12606430053711,
            "gru_rmse": 214741.859375,
            "hybrid_mape": 30.601995314854257,
            "hybrid_rmse": 159086.50214307598
        }
    },
    "2000-01-01": {
        "Tax Revenues": {
            "order": [
                0,
                1,
                3
            ],
            "seasonal_order": [
                0,
                1,
                0,
                3
            ],
            "gru_mape": 14.56957721710205,
            "gru_rmse": 65587.375,
            "hybrid_mape": 13.872030455784598,
            "hybrid_rmse": 61403.581247514834
        },
        "BIR": {
            "order": [
                2,
                1,
                3
            ],
            "seasonal_order": [
                0,
                1,
                0,
                3
            ],
            "gru_mape": 14.166543960571289,
            "gru_rmse": 53356.96484375,
            "hybrid_mape": 11.265136101577632,
            "hybrid_rmse": 43023.54223289034
        },
        "BOC": {
            "order": [
                1,
                1,
                5
            ],
            "seasonal_order": [
                0,
                0,
                1,
                12
            ],
            "gru_mape": 36.72601318359375,
            "gru_rmse": 27803.6875,
            "hybrid_mape": 18.441945467494943,
            "hybrid_rmse": 15884.710550913976
        },
        "Other Offices": {
            "order": [
                0,
                1,
                2
            ],
            "seasonal_order": [
                0,
                1,
                0,
                3
            ],
            "gru_mape": 28.874099731445312,
            "gru_rmse": 943.9423828125,
            "hybrid_mape": 37.92726872370522,
            "hybrid_rmse": 954.3281334706485
        },
        "Expenditures": {
            "order": [
                4,
                0,
                6
            ],
            "seasonal_order": [
                0,
                1,
                0,
                6
            ],
            "gru_mape": 34.17156219482422,
            "gru_rmse": 179407.46875,
            "hybrid_mape": 17.473734923522127,
            "hybrid_rmse": 100979.71652365987
        }
    },
    "2007-01-01": {
        "Tax Revenues": {
            "order": [
                0,
                0,
                0
            ],
            "seasonal_order": [
                0,
                0,
                0,
                0
            ],
            "gru_mape": 17.1414794921875,
            "gru_rmse": 77956.78125,
            "hybrid_mape": 17.14148009122612,
            "hybrid_rmse": 77956.77731019647
        },
        "BIR": {
            "order": [
                0,
                0,
                0
            ],
            "seasonal_order": [
                0,
                0,
                0,
                0
            ],
            "gru_mape": 16.71084976196289,
            "gru_rmse": 64883.25390625,
            "hybrid_mape": 16.710849994499807,
            "hybrid_rmse": 64883.25428790249
        },
        "BOC": {
            "order": [
                0,
                0,
                0
            ],
            "seasonal_order": [
                0,
                0,
                0,
                0
            ],
            "gru_mape": 26.57374382019043,
            "gru_rmse": 20834.462890625,
            "hybrid_mape": 26.573741401351132,
            "hybrid_rmse": 20834.463604890603
        },
        "Other Offices": {
            "order": [
                0,
                0,
                5
            ],
            "seasonal_order": [
                0,
                1,
                0,
                12
            ],
            "gru_mape": 30.32573127746582,
            "gru_rmse": 939.7593994140625,
            "hybrid_mape": 16.479931236765715,
            "hybrid_rmse": 499.86466156864793
        },
        "Expenditures": {
            "order": [
                3,
                0,
                2
            ],
            "seasonal_order": [
                1,
                1,
                1,
                6
            ],
            "gru_mape": 23.919408798217773,
            "gru_rmse": 144124.5,
            "hybrid_mape": 13.701509121584015,
            "hybrid_rmse": 82755.99984927186
        }
    }
}